__init__.py
cli/__init__.py
cli/__main__.py
cli/main.py
core/__init__.py
bus_cli-0.0.0.dist-info/METADATA
bus_cli-0.0.0.dist-info/WHEEL
bus_cli-0.0.0.dist-info/entry_points.txt
bus_cli-0.0.0.dist-info/top_level.txt
bus_cli-0.0.0.dist-info/RECORD
