Metadata-Version: 2.1
Name: bus-cli
Version: 0.0.0
Summary: Bus, the ultimate configuration manager.
Author-email: Jordan Jimenez <jordanjimenez510@gmail.com>, Luciano Remes <cybergenik@gmail.com>, Yifei Sun <yifei@email.com>
License: UNKNOWN
Project-URL: Repository, https://github.com/bus-sh/bus-cli
Platform: UNKNOWN
Classifier: Environment :: Console
Classifier: Programming Language :: Python
Classifier: Programming Language :: Python :: 3 :: Only
Requires-Python: >=3.7
